<?xml version="1.0"?>
<method xmlns:xsi="http://www.w3.org/2001/XMLSchema-instance" xmlns:xsd="http://www.w3.org/2001/XMLSchema" id="4f262711-d70c-4339-b90c-55e559e3686b" lastModifiedUtc="2014-05-05T11:31:42.8105518Z" name="OnAfterUpdate" methodType="CrudEvent" actionType="None" returnMode="None">
  <extendedMetaData />
  <ExtendedPropertiesCollection>
    <extendee type="Sage.Platform.Orm.Entities.OrmEntityMethod" />
  </ExtendedPropertiesCollection>
  <parameter />
  <preExecuteTargets />
  <methodTargets>
    <methodTarget id="a4d902c4-d759-4b0b-8727-e778d9d8ec45" lastModifiedUtc="2014-05-05T11:31:42.7013516Z" targetType="Sage.Platform.Orm.DefaultCRUDEventHandler, Sage.Platform" targetMethod="OnAfterUpdate" active="true">
      <ExtendedPropertiesCollection>
        <extendee type="Sage.Platform.Orm.Entities.OrmMethodTarget" />
      </ExtendedPropertiesCollection>
    </methodTarget>
  </methodTargets>
  <postExecuteTargets />
  <postFlushTargets />
</method>