<?xml version="1.0" encoding="utf-8"?><index><stem n="depend"><phr n="Depending"><ent r="3" t="0" w="80" /><ent r="3" t="21" w="644" /><ent r="3" t="34" w="100" /><ent r="3" t="44" w="181" /><ent r="3" t="45" w="42" /><ent r="3" t="50" w="139" /><ent r="4" t="68" w="189" /><ent r="10" t="82" w="513" /><ent r="11" t="82" w="828" /><ent r="11" t="82" w="1143" /><ent r="6" t="82" w="2963" /><ent r="4" t="114" w="106" /><ent r="4" t="114" w="250" /><ent r="3" t="119" w="159" /><ent r="6" t="153" w="180" /><ent r="7" t="188" w="1218" /><ent r="7" t="188" w="1269" /><ent r="6" t="226" w="112" /><ent r="8" t="294" w="249" /><ent r="6" t="314" w="179" /><ent r="6" t="320" w="340" /><ent r="4" t="324" w="152" /><ent r="55" t="327" w="216" /><ent r="7" t="375" w="492" /><ent r="7" t="392" w="77" /><ent r="7" t="392" w="163" /><ent r="4" t="423" w="371" /><ent r="3" t="432" w="28" /><ent r="3" t="493" w="157" /><ent r="3" t="494" w="335" /><ent r="6" t="563" w="223" /><ent r="4" t="670" w="106" /><ent r="4" t="679" w="204" /><ent r="7" t="698" w="451" /></phr><phr n="depending"><ent r="3" t="0" w="123" /><ent r="7" t="7" w="72" /><ent r="55" t="8" w="131" /><ent r="3" t="39" w="178" /><ent r="7" t="44" w="74" /><ent r="3" t="50" w="112" /><ent r="7" t="63" w="51" /><ent r="3" t="119" w="46" /><ent r="7" t="128" w="51" /><ent r="3" t="145" w="67" /><ent r="3" t="176" w="86" /><ent r="7" t="200" w="67" /><ent r="3" t="214" w="39" /><ent r="3" t="237" w="163" /><ent r="3" t="334" w="120" /><ent r="7" t="356" w="436" /><ent r="3" t="388" w="56" /><ent r="6" t="412" w="466" /><ent r="7" t="443" w="45" /><ent r="3" t="449" w="39" /><ent r="6" t="459" w="327" /><ent r="7" t="474" w="72" /><ent r="7" t="493" w="31" /><ent r="6" t="501" w="118" /><ent r="7" t="504" w="53" /><ent r="7" t="520" w="47" /><ent r="3" t="599" w="319" /><ent r="3" t="626" w="39" /><ent r="6" t="630" w="252" /></phr><phr n="depend"><ent r="6" t="11" w="404" /><ent r="3" t="44" w="210" /><ent r="3" t="103" w="41" /><ent r="3" t="108" w="36" /><ent r="6" t="168" w="51" /><ent r="7" t="169" w="86" /><ent r="6" t="170" w="99" /><ent r="8" t="171" w="82" /><ent r="6" t="172" w="62" /><ent r="3" t="198" w="1429" /><ent r="7" t="375" w="226" /><ent r="7" t="375" w="239" /><ent r="3" t="392" w="33" /><ent r="3" t="394" w="33" /><ent r="5" t="394" w="212" /><ent r="6" t="408" w="209" /><ent r="3" t="413" w="47" /><ent r="3" t="460" w="141" /><ent r="8" t="494" w="148" /><ent r="3" t="577" w="38" /><ent r="3" t="578" w="58" /><ent r="3" t="582" w="37" /><ent r="3" t="585" w="69" /><ent r="3" t="586" w="34" /><ent r="3" t="602" w="83" /><ent r="7" t="661" w="99" /><ent r="7" t="661" w="112" /><ent r="4" t="679" w="313" /><ent r="4" t="682" w="178" /><ent r="3" t="694" w="78" /><ent r="7" t="698" w="180" /><ent r="7" t="698" w="193" /></phr><phr n="depends"><ent r="3" t="61" w="45" /><ent r="7" t="147" w="207" /><ent r="7" t="147" w="617" /><ent r="5" t="148" w="196" /><ent r="5" t="149" w="201" /><ent r="3" t="155" w="66" /><ent r="6" t="196" w="168" /><ent r="6" t="433" w="359" /><ent r="3" t="551" w="54" /><ent r="6" t="560" w="184" /><ent r="3" t="572" w="32" /><ent r="3" t="652" w="129" /><ent r="6" t="656" w="114" /><ent r="6" t="656" w="167" /><ent r="6" t="656" w="198" /><ent r="6" t="656" w="227" /></phr><phr n="dependent"><ent r="15" t="82" w="405" /><ent r="15" t="82" w="698" /><ent r="15" t="82" w="1013" /><ent r="15" t="82" w="1314" /><ent r="15" t="82" w="1547" /><ent r="4" t="445" w="653" /><ent r="7" t="597" w="30" /><ent r="7" t="597" w="176" /></phr><phr n="dependant"><ent r="4" t="502" w="830" /></phr></stem><stem n="what"><phr n="what"><ent r="3" t="0" w="82" /><ent r="3" t="15" w="157" /><ent r="4" t="16" w="116" /><ent r="4" t="18" w="211" /><ent r="4" t="25" w="130" /><ent r="3" t="39" w="27" /><ent r="4" t="39" w="298" /><ent r="8" t="51" w="607" /><ent r="6" t="54" w="50" /><ent r="6" t="55" w="50" /><ent r="6" t="57" w="39" /><ent r="3" t="60" w="77" /><ent r="6" t="62" w="55" /><ent r="6" t="64" w="34" /><ent r="6" t="69" w="285" /><ent r="6" t="70" w="51" /><ent r="6" t="71" w="50" /><ent r="5" t="85" w="550" /><ent r="5" t="85" w="724" /><ent r="6" t="88" w="49" /><ent r="6" t="89" w="65" /><ent r="6" t="90" w="50" /><ent r="3" t="92" w="19" /><ent r="6" t="94" w="50" /><ent r="6" t="95" w="81" /><ent r="6" t="96" w="46" /><ent r="6" t="101" w="81" /><ent r="6" t="102" w="43" /><ent r="6" t="103" w="53" /><ent r="6" t="105" w="50" /><ent r="6" t="106" w="50" /><ent r="6" t="107" w="27" /><ent r="6" t="108" w="79" /><ent r="6" t="110" w="61" /><ent r="6" t="111" w="299" /><ent r="6" t="119" w="200" /><ent r="6" t="120" w="182" /><ent r="6" t="121" w="126" /><ent r="6" t="127" w="50" /><ent r="6" t="137" w="50" /><ent r="6" t="138" w="49" /><ent r="3" t="173" w="239" /><ent r="3" t="183" w="19" /><ent r="6" t="215" w="276" /><ent r="3" t="228" w="117" /><ent r="3" t="228" w="131" /><ent r="6" t="230" w="112" /><ent r="3" t="237" w="52" /><ent r="3" t="237" w="69" /><ent r="3" t="242" w="58" /><ent r="3" t="242" w="75" /><ent r="6" t="333" w="87" /><ent r="6" t="342" w="171" /><ent r="6" t="350" w="47" /><ent r="6" t="356" w="19" /><ent r="6" t="360" w="54" /><ent r="4" t="373" w="476" /><ent r="3" t="384" w="14" /><ent r="6" t="408" w="197" /><ent r="3" t="435" w="36" /><ent r="3" t="436" w="36" /><ent r="3" t="436" w="66" /><ent r="3" t="437" w="31" /><ent r="4" t="446" w="202" /><ent r="54" t="487" w="61" /><ent r="6" t="585" w="264" /><ent r="3" t="621" w="79" /><ent r="6" t="623" w="70" /><ent r="6" t="695" w="119" /><ent r="4" t="707" w="165" /><ent r="8" t="707" w="420" /></phr><phr n="What"><ent r="64" t="0" w="152" /><ent r="1000" t="3" w="1" /><ent r="100" t="3" w="8" /><ent r="102" t="3" w="15" /><ent r="4" t="5" w="121" /><ent r="65" t="7" w="129" /><ent r="65" t="7" w="133" /><ent r="65" t="7" w="224" /><ent r="65" t="7" w="245" /><ent r="65" t="7" w="262" /><ent r="65" t="7" w="409" /><ent r="64" t="33" w="268" /><ent r="1000" t="34" w="1" /><ent r="102" t="34" w="23" /><ent r="64" t="36" w="420" /><ent r="64" t="38" w="268" /><ent r="1000" t="39" w="1" /><ent r="102" t="39" w="8" /><ent r="64" t="40" w="203" /><ent r="1000" t="53" w="1" /><ent r="102" t="53" w="10" /><ent r="64" t="53" w="203" /><ent r="64" t="53" w="207" /><ent r="64" t="53" w="211" /><ent r="64" t="60" w="153" /><ent r="1000" t="61" w="1" /><ent r="102" t="61" w="10" /><ent r="64" t="67" w="80" /><ent r="1000" t="69" w="1" /><ent r="102" t="69" w="10" /><ent r="64" t="75" w="65" /><ent r="1000" t="76" w="1" /><ent r="102" t="76" w="10" /><ent r="1000" t="87" w="1" /><ent r="153" t="87" w="5" /><ent r="1000" t="93" w="1" /><ent r="102" t="93" w="7" /><ent r="1000" t="99" w="1" /><ent r="153" t="99" w="10" /><ent r="1000" t="109" w="1" /><ent r="102" t="109" w="11" /><ent r="1000" t="111" w="1" /><ent r="102" t="111" w="22" /><ent r="68" t="112" w="888" /><ent r="64" t="112" w="1032" /><ent r="64" t="119" w="913" /><ent r="1000" t="120" w="1" /><ent r="102" t="120" w="10" /><ent r="1000" t="123" w="1" /><ent r="102" t="123" w="10" /><ent r="1000" t="126" w="1" /><ent r="102" t="126" w="10" /><ent r="64" t="133" w="102" /><ent r="1000" t="139" w="1" /><ent r="102" t="139" w="11" /><ent r="64" t="139" w="67" /><ent r="64" t="139" w="71" /><ent r="64" t="139" w="75" /><ent r="64" t="139" w="79" /><ent r="64" t="140" w="286" /><ent r="1000" t="152" w="1" /><ent r="102" t="152" w="8" /><ent r="1000" t="158" w="1" /><ent r="102" t="158" w="13" /><ent r="153" t="165" w="20" /><ent r="3" t="198" w="1041" /><ent r="64" t="202" w="188" /><ent r="64" t="208" w="183" /><ent r="64" t="214" w="279" /><ent r="1000" t="215" w="1" /><ent r="64" t="233" w="356" /><ent r="64" t="234" w="421" /><ent r="64" t="235" w="191" /><ent r="64" t="236" w="224" /><ent r="64" t="237" w="327" /><ent r="64" t="239" w="219" /><ent r="64" t="240" w="289" /><ent r="64" t="241" w="198" /><ent r="64" t="242" w="280" /><ent r="64" t="243" w="248" /><ent r="64" t="278" w="196" /><ent r="64" t="294" w="401" /><ent r="1000" t="296" w="1" /><ent r="102" t="296" w="5" /><ent r="64" t="296" w="140" /><ent r="64" t="301" w="242" /><ent r="64" t="303" w="299" /><ent r="64" t="340" w="84" /><ent r="64" t="341" w="633" /><ent r="1000" t="346" w="1" /><ent r="102" t="346" w="11" /><ent r="4" t="346" w="84" /><ent r="4" t="346" w="463" /><ent r="4" t="361" w="142" /><ent r="6" t="388" w="71" /><ent r="4" t="399" w="158" /><ent r="64" t="453" w="451" /><ent r="64" t="524" w="230" /><ent r="1000" t="588" w="1" /><ent r="102" t="588" w="9" /><ent r="6" t="588" w="91" /><ent r="3" t="620" w="214" /><ent r="65" t="620" w="227" /><ent r="64" t="621" w="225" /><ent r="7" t="621" w="317" /><ent r="7" t="621" w="367" /><ent r="64" t="621" w="424" /><ent r="64" t="621" w="435" /><ent r="1000" t="622" w="1" /><ent r="100" t="622" w="5" /><ent r="100" t="622" w="9" /><ent r="102" t="622" w="15" /><ent r="3" t="622" w="20" /><ent r="3" t="622" w="70" /><ent r="3" t="622" w="123" /><ent r="5" t="622" w="133" /><ent r="4" t="622" w="141" /><ent r="1000" t="623" w="1" /><ent r="100" t="623" w="9" /><ent r="100" t="623" w="14" /><ent r="102" t="623" w="18" /><ent r="3" t="623" w="35" /><ent r="3" t="623" w="54" /><ent r="5" t="623" w="106" /><ent r="7" t="623" w="117" /><ent r="6" t="623" w="144" /><ent r="64" t="623" w="260" /><ent r="1000" t="625" w="1" /><ent r="102" t="625" w="14" /><ent r="64" t="627" w="202" /><ent r="64" t="663" w="243" /><ent r="1000" t="664" w="1" /><ent r="102" t="664" w="16" /></phr></stem><stem n="system"><phr n="system"><ent r="3" t="0" w="84" /><ent r="3" t="0" w="107" /><ent r="3" t="0" w="142" /><ent r="3" t="2" w="299" /><ent r="3" t="2" w="309" /><ent r="3" t="2" w="390" /><ent r="3" t="4" w="162" /><ent r="3" t="5" w="39" /><ent r="3" t="5" w="79" /><ent r="4" t="6" w="74" /><ent r="4" t="6" w="110" /><ent r="4" t="6" w="132" /><ent r="4" t="6" w="153" /><ent r="3" t="8" w="42" /><ent r="4" t="8" w="187" /><ent r="4" t="8" w="209" /><ent r="3" t="10" w="17" /><ent r="4" t="10" w="187" /><ent r="6" t="11" w="734" /><ent r="6" t="12" w="20" /><ent r="6" t="13" w="19" /><ent r="6" t="14" w="23" /><ent r="6" t="15" w="18" /><ent r="6" t="16" w="28" /><ent r="6" t="17" w="36" /><ent r="6" t="18" w="20" /><ent r="3" t="18" w="153" /><ent r="6" t="19" w="28" /><ent r="3" t="19" w="317" /><ent r="3" t="19" w="350" /><ent r="6" t="20" w="18" /><ent r="3" t="21" w="385" /><ent r="5" t="21" w="716" /><ent r="3" t="21" w="733" /><ent r="3" t="21" w="752" /><ent r="3" t="21" w="788" /><ent r="3" t="21" w="804" /><ent r="3" t="21" w="853" /><ent r="6" t="22" w="22" /><ent r="6" t="23" w="10" /><ent r="6" t="25" w="14" /><ent r="4" t="25" w="186" /><ent r="5" t="26" w="56" /><ent r="4" t="28" w="116" /><ent r="6" t="29" w="26" /><ent r="4" t="29" w="105" /><ent r="6" t="30" w="19" /><ent r="6" t="32" w="10" /><ent r="6" t="33" w="21" /><ent r="6" t="35" w="23" /><ent r="6" t="38" w="10" /><ent r="6" t="40" w="19" /><ent r="3" t="41" w="112" /><ent r="6" t="43" w="20" /><ent r="6" t="44" w="18" /><ent r="3" t="45" w="41" /><ent r="3" t="49" w="49" /><ent r="4" t="49" w="75" /><ent r="100" t="50" w="16" /><ent r="3" t="50" w="38" /><ent r="3" t="50" w="76" /><ent r="3" t="50" w="116" /><ent r="3" t="50" w="127" /><ent r="6" t="50" w="214" /><ent r="4" t="51" w="44" /><ent r="8" t="51" w="580" /><ent r="8" t="51" w="645" /><ent r="8" t="51" w="660" /><ent r="4" t="51" w="770" /><ent r="6" t="52" w="12" /><ent r="100" t="52" w="35" /><ent r="3" t="63" w="304" /><ent r="100" t="68" w="36" /><ent r="3" t="68" w="68" /><ent r="6" t="68" w="170" /><ent r="6" t="76" w="127" /><ent r="6" t="76" w="138" /><ent r="6" t="79" w="55" /><ent r="15" t="82" w="417" /><ent r="15" t="82" w="710" /><ent r="15" t="82" w="1025" /><ent r="15" t="82" w="1326" /><ent r="15" t="82" w="1559" /><ent r="3" t="99" w="48" /><ent r="3" t="123" w="254" /><ent r="6" t="129" w="142" /><ent r="7" t="144" w="226" /><ent r="5" t="145" w="280" /><ent r="3" t="146" w="214" /><ent r="6" t="146" w="242" /><ent r="3" t="152" w="75" /><ent r="3" t="155" w="71" /><ent r="55" t="157" w="512" /><ent r="7" t="169" w="111" /><ent r="3" t="173" w="160" /><ent r="3" t="173" w="176" /><ent r="7" t="175" w="48" /><ent r="3" t="175" w="93" /><ent r="3" t="175" w="136" /><ent r="6" t="175" w="291" /><ent r="4" t="181" w="172" /><ent r="3" t="187" w="101" /><ent r="3" t="187" w="114" /><ent r="4" t="187" w="184" /><ent r="3" t="189" w="113" /><ent r="3" t="189" w="126" /><ent r="6" t="195" w="356" /><ent r="6" t="195" w="389" /><ent r="6" t="195" w="461" /><ent r="6" t="195" w="494" /><ent r="6" t="196" w="172" /><ent r="3" t="198" w="32" /><ent r="3" t="198" w="781" /><ent r="6" t="233" w="12" /><ent r="6" t="233" w="27" /><ent r="6" t="234" w="16" /><ent r="6" t="234" w="31" /><ent r="6" t="235" w="28" /><ent r="6" t="236" w="14" /><ent r="6" t="240" w="16" /><ent r="6" t="240" w="31" /><ent r="6" t="241" w="8" /><ent r="6" t="241" w="23" /><ent r="6" t="242" w="8" /><ent r="6" t="242" w="23" /><ent r="6" t="243" w="16" /><ent r="6" t="243" w="31" /><ent r="6" t="244" w="19" /><ent r="6" t="245" w="24" /><ent r="6" t="251" w="16" /><ent r="6" t="253" w="21" /><ent r="6" t="254" w="13" /><ent r="6" t="260" w="22" /><ent r="6" t="262" w="13" /><ent r="3" t="265" w="76" /><ent r="6" t="266" w="76" /><ent r="6" t="272" w="12" /><ent r="100" t="274" w="9" /><ent r="100" t="274" w="15" /><ent r="64" t="279" w="55" /><ent r="3" t="279" w="65" /><ent r="4" t="280" w="92" /><ent r="4" t="280" w="145" /><ent r="4" t="280" w="170" /><ent r="4" t="280" w="285" /><ent r="3" t="280" w="378" /><ent r="3" t="281" w="67" /><ent r="3" t="288" w="39" /><ent r="6" t="356" w="51" /><ent r="6" t="356" w="492" /><ent r="6" t="356" w="589" /><ent r="6" t="356" w="623" /><ent r="3" t="364" w="49" /><ent r="3" t="373" w="45" /><ent r="6" t="373" w="361" /><ent r="4" t="373" w="480" /><ent r="6" t="375" w="629" /><ent r="3" t="378" w="44" /><ent r="6" t="384" w="25" /><ent r="6" t="387" w="47" /><ent r="11" t="387" w="395" /><ent r="8" t="394" w="106" /><ent r="3" t="404" w="30" /><ent r="4" t="413" w="124" /><ent r="4" t="413" w="131" /><ent r="4" t="413" w="149" /><ent r="3" t="414" w="50" /><ent r="6" t="414" w="115" /><ent r="6" t="414" w="127" /><ent r="3" t="415" w="52" /><ent r="100" t="416" w="10" /><ent r="4" t="416" w="85" /><ent r="4" t="416" w="108" /><ent r="3" t="416" w="197" /><ent r="4" t="416" w="212" /><ent r="4" t="416" w="218" /><ent r="4" t="416" w="230" /><ent r="4" t="416" w="234" /><ent r="4" t="416" w="240" /><ent r="4" t="416" w="260" /><ent r="4" t="416" w="269" /><ent r="3" t="418" w="42" /><ent r="3" t="421" w="20" /><ent r="100" t="422" w="14" /><ent r="3" t="422" w="45" /><ent r="3" t="422" w="68" /><ent r="3" t="423" w="41" /><ent r="3" t="423" w="66" /><ent r="4" t="423" w="123" /><ent r="9" t="423" w="305" /><ent r="9" t="423" w="324" /><ent r="3" t="424" w="28" /><ent r="100" t="425" w="18" /><ent r="3" t="425" w="42" /><ent r="6" t="425" w="54" /><ent r="3" t="426" w="33" /><ent r="8" t="426" w="108" /><ent r="8" t="426" w="119" /><ent r="8" t="427" w="69" /><ent r="3" t="428" w="24" /><ent r="8" t="428" w="120" /><ent r="8" t="428" w="196" /><ent r="9" t="428" w="207" /><ent r="9" t="428" w="240" /><ent r="9" t="428" w="261" /><ent r="5" t="430" w="67" /><ent r="6" t="432" w="143" /><ent r="6" t="432" w="187" /><ent r="7" t="432" w="292" /><ent r="6" t="433" w="303" /><ent r="6" t="433" w="322" /><ent r="6" t="433" w="344" /><ent r="6" t="434" w="247" /><ent r="3" t="439" w="138" /><ent r="100" t="440" w="23" /><ent r="3" t="440" w="78" /><ent r="6" t="440" w="199" /><ent r="7" t="440" w="312" /><ent r="7" t="440" w="340" /><ent r="7" t="440" w="355" /><ent r="3" t="445" w="50" /><ent r="3" t="445" w="62" /><ent r="4" t="445" w="308" /><ent r="4" t="445" w="442" /><ent r="4" t="445" w="576" /><ent r="4" t="445" w="619" /><ent r="4" t="446" w="211" /><ent r="3" t="447" w="121" /><ent r="6" t="478" w="43" /><ent r="6" t="478" w="58" /><ent r="6" t="479" w="103" /><ent r="6" t="480" w="269" /><ent r="6" t="480" w="284" /><ent r="6" t="481" w="16" /><ent r="6" t="482" w="18" /><ent r="6" t="483" w="17" /><ent r="6" t="484" w="16" /><ent r="6" t="486" w="21" /><ent r="3" t="498" w="64" /><ent r="6" t="504" w="18" /><ent r="6" t="505" w="25" /><ent r="6" t="506" w="25" /><ent r="6" t="507" w="25" /><ent r="6" t="508" w="21" /><ent r="6" t="509" w="16" /><ent r="6" t="510" w="16" /><ent r="6" t="511" w="32" /><ent r="6" t="512" w="21" /><ent r="6" t="513" w="29" /><ent r="6" t="514" w="29" /><ent r="6" t="515" w="29" /><ent r="6" t="516" w="25" /><ent r="6" t="524" w="16" /><ent r="6" t="527" w="14" /><ent r="6" t="528" w="14" /><ent r="6" t="529" w="18" /><ent r="3" t="529" w="78" /><ent r="6" t="530" w="25" /><ent r="3" t="530" w="78" /><ent r="6" t="531" w="25" /><ent r="6" t="532" w="25" /><ent r="54" t="532" w="68" /><ent r="6" t="533" w="21" /><ent r="6" t="534" w="10" /><ent r="6" t="535" w="18" /><ent r="6" t="536" w="12" /><ent r="6" t="537" w="8" /><ent r="4" t="537" w="108" /><ent r="3" t="546" w="73" /><ent r="6" t="550" w="255" /><ent r="6" t="550" w="280" /><ent r="3" t="556" w="29" /><ent r="6" t="560" w="188" /><ent r="6" t="568" w="24" /><ent r="6" t="569" w="24" /><ent r="6" t="570" w="18" /><ent r="3" t="600" w="49" /><ent r="3" t="601" w="50" /><ent r="6" t="616" w="135" /><ent r="3" t="617" w="97" /><ent r="4" t="620" w="263" /><ent r="4" t="620" w="283" /><ent r="3" t="621" w="75" /><ent r="4" t="621" w="125" /><ent r="54" t="624" w="171" /><ent r="3" t="625" w="53" /><ent r="3" t="625" w="283" /><ent r="6" t="634" w="18" /><ent r="6" t="656" w="21" /><ent r="6" t="656" w="271" /><ent r="3" t="657" w="57" /><ent r="3" t="657" w="134" /><ent r="6" t="658" w="184" /><ent r="4" t="658" w="229" /><ent r="6" t="660" w="21" /><ent r="6" t="662" w="21" /><ent r="6" t="663" w="26" /><ent r="6" t="665" w="19" /><ent r="6" t="666" w="19" /><ent r="6" t="667" w="21" /><ent r="6" t="668" w="35" /><ent r="6" t="669" w="19" /><ent r="6" t="685" w="320" /><ent r="6" t="697" w="331" /><ent r="6" t="697" w="373" /><ent r="6" t="697" w="419" /><ent r="6" t="697" w="442" /><ent r="6" t="697" w="467" /><ent r="6" t="697" w="492" /><ent r="3" t="707" w="40" /><ent r="8" t="707" w="315" /><ent r="8" t="707" w="424" /></phr><phr n="System"><ent r="1000" t="4" w="4" /><ent r="102" t="4" w="11" /><ent r="7" t="5" w="239" /><ent r="65" t="7" w="391" /><ent r="67" t="20" w="236" /><ent r="100" t="21" w="42" /><ent r="5" t="23" w="382" /><ent r="65" t="25" w="294" /><ent r="5" t="51" w="145" /><ent r="64" t="51" w="834" /><ent r="1000" t="68" w="6" /><ent r="102" t="68" w="13" /><ent r="9" t="68" w="154" /><ent r="67" t="68" w="209" /><ent r="6" t="78" w="232" /><ent r="8" t="82" w="2303" /><ent r="6" t="175" w="25" /><ent r="9" t="176" w="17" /><ent r="6" t="177" w="34" /><ent r="6" t="178" w="15" /><ent r="5" t="245" w="129" /><ent r="4" t="245" w="147" /><ent r="5" t="268" w="332" /><ent r="5" t="270" w="417" /><ent r="1000" t="274" w="4" /><ent r="102" t="274" w="24" /><ent r="3" t="274" w="30" /><ent r="5" t="274" w="85" /><ent r="3" t="281" w="69" /><ent r="7" t="286" w="133" /><ent r="9" t="380" w="678" /><ent r="9" t="380" w="1112" /><ent r="65" t="413" w="85" /><ent r="5" t="416" w="81" /><ent r="64" t="416" w="294" /><ent r="1000" t="427" w="4" /><ent r="102" t="427" w="9" /><ent r="3" t="427" w="15" /><ent r="5" t="427" w="55" /><ent r="8" t="427" w="64" /><ent r="6" t="432" w="195" /><ent r="6" t="433" w="120" /><ent r="6" t="433" w="436" /><ent r="6" t="550" w="231" /><ent r="6" t="550" w="291" /><ent r="6" t="560" w="236" /><ent r="6" t="590" w="24" /><ent r="6" t="600" w="21" /><ent r="6" t="601" w="24" /><ent r="6" t="616" w="31" /><ent r="6" t="685" w="347" /></phr><phr n="systems"><ent r="3" t="4" w="15" /><ent r="3" t="41" w="34" /><ent r="3" t="42" w="43" /><ent r="6" t="51" w="261" /><ent r="8" t="51" w="614" /><ent r="3" t="68" w="84" /><ent r="4" t="68" w="192" /><ent r="3" t="187" w="54" /><ent r="3" t="187" w="61" /><ent r="4" t="187" w="168" /><ent r="3" t="189" w="66" /><ent r="3" t="189" w="73" /><ent r="4" t="189" w="165" /><ent r="3" t="416" w="38" /><ent r="3" t="416" w="56" /><ent r="3" t="416" w="59" /><ent r="4" t="416" w="255" /><ent r="10" t="422" w="223" /><ent r="8" t="423" w="347" /><ent r="3" t="427" w="28" /><ent r="6" t="433" w="143" /><ent r="3" t="434" w="67" /><ent r="3" t="440" w="52" /></phr><phr n="Systems"><ent r="3" t="21" w="270" /></phr></stem><stem n="instal"><phr n="installed"><ent r="3" t="0" w="86" /><ent r="10" t="72" w="257" /><ent r="6" t="123" w="25" /><ent r="3" t="147" w="89" /><ent r="6" t="152" w="189" /><ent r="4" t="181" w="108" /><ent r="6" t="181" w="129" /><ent r="6" t="181" w="137" /><ent r="4" t="181" w="235" /><ent r="5" t="195" w="62" /><ent r="5" t="195" w="66" /><ent r="6" t="195" w="80" /><ent r="6" t="195" w="98" /><ent r="6" t="195" w="103" /><ent r="6" t="195" w="107" /><ent r="6" t="195" w="113" /><ent r="10" t="195" w="137" /><ent r="5" t="195" w="169" /><ent r="5" t="195" w="173" /><ent r="5" t="195" w="246" /><ent r="5" t="195" w="250" /><ent r="6" t="196" w="85" /><ent r="6" t="196" w="103" /><ent r="6" t="196" w="108" /><ent r="6" t="196" w="112" /><ent r="6" t="196" w="118" /><ent r="10" t="196" w="142" /><ent r="6" t="196" w="228" /><ent r="6" t="196" w="246" /><ent r="6" t="196" w="251" /><ent r="6" t="196" w="255" /><ent r="6" t="196" w="261" /><ent r="10" t="196" w="285" /><ent r="6" t="196" w="591" /><ent r="3" t="198" w="454" /><ent r="6" t="279" w="19" /><ent r="6" t="281" w="35" /><ent r="54" t="320" w="32" /><ent r="6" t="380" w="352" /><ent r="7" t="380" w="451" /><ent r="7" t="380" w="466" /><ent r="7" t="380" w="528" /><ent r="7" t="380" w="543" /><ent r="6" t="380" w="621" /><ent r="6" t="380" w="842" /><ent r="7" t="380" w="992" /><ent r="7" t="380" w="1007" /><ent r="6" t="380" w="1055" /><ent r="8" t="554" w="339" /><ent r="6" t="560" w="101" /><ent r="6" t="560" w="119" /><ent r="6" t="560" w="124" /><ent r="6" t="560" w="128" /><ent r="6" t="560" w="134" /><ent r="10" t="560" w="158" /><ent r="6" t="620" w="166" /><ent r="6" t="654" w="23" /><ent r="6" t="655" w="32" /></phr><phr n="installation"><ent r="3" t="0" w="131" /><ent r="7" t="7" w="80" /><ent r="7" t="63" w="59" /><ent r="7" t="128" w="59" /><ent r="7" t="200" w="75" /><ent r="70" t="311" w="166" /><ent r="71" t="320" w="148" /><ent r="5" t="380" w="1133" /><ent r="6" t="380" w="1154" /><ent r="6" t="380" w="1182" /><ent r="7" t="443" w="53" /><ent r="7" t="474" w="80" /><ent r="70" t="480" w="377" /><ent r="7" t="493" w="39" /><ent r="7" t="504" w="61" /><ent r="7" t="520" w="55" /></phr><phr n="Installing"><ent r="65" t="7" w="96" /><ent r="64" t="8" w="245" /><ent r="1000" t="380" w="1" /><ent r="102" t="380" w="8" /><ent r="6" t="380" w="1157" /></phr><phr n="installing"><ent r="4" t="10" w="78" /><ent r="6" t="181" w="139" /><ent r="10" t="195" w="140" /><ent r="10" t="196" w="145" /><ent r="10" t="196" w="288" /><ent r="12" t="380" w="273" /><ent r="12" t="380" w="773" /><ent r="10" t="560" w="161" /></phr><phr n="install"><ent r="118" t="123" w="60" /><ent r="120" t="144" w="132" /><ent r="119" t="146" w="97" /><ent r="118" t="147" w="118" /><ent r="118" t="148" w="83" /><ent r="118" t="149" w="96" /><ent r="118" t="150" w="130" /><ent r="6" t="181" w="121" /><ent r="67" t="195" w="86" /><ent r="6" t="195" w="211" /><ent r="6" t="195" w="282" /><ent r="67" t="196" w="91" /><ent r="67" t="196" w="234" /><ent r="69" t="196" w="596" /><ent r="9" t="311" w="207" /><ent r="70" t="311" w="228" /><ent r="9" t="311" w="240" /><ent r="9" t="320" w="203" /><ent r="70" t="320" w="224" /><ent r="9" t="320" w="236" /><ent r="8" t="380" w="254" /><ent r="6" t="380" w="366" /><ent r="6" t="380" w="375" /><ent r="6" t="380" w="435" /><ent r="6" t="380" w="478" /><ent r="6" t="380" w="504" /><ent r="6" t="380" w="555" /><ent r="6" t="380" w="584" /><ent r="6" t="380" w="596" /><ent r="5" t="380" w="707" /><ent r="8" t="380" w="754" /><ent r="6" t="380" w="856" /><ent r="6" t="380" w="956" /><ent r="6" t="380" w="1017" /><ent r="6" t="380" w="1029" /><ent r="6" t="380" w="1186" /><ent r="118" t="382" w="57" /><ent r="65" t="399" w="707" /><ent r="120" t="488" w="452" /><ent r="120" t="498" w="92" /><ent r="67" t="560" w="107" /><ent r="12" t="563" w="156" /><ent r="73" t="563" w="177" /><ent r="12" t="563" w="189" /><ent r="118" t="656" w="52" /></phr><phr n="Install"><ent r="5" t="380" w="193" /><ent r="9" t="380" w="222" /><ent r="9" t="380" w="247" /><ent r="7" t="380" w="611" /><ent r="5" t="380" w="696" /><ent r="9" t="380" w="729" /><ent r="9" t="380" w="747" /><ent r="7" t="380" w="1045" /><ent r="5" t="399" w="716" /><ent r="6" t="412" w="293" /></phr><phr n="Installed"><ent r="12" t="380" w="283" /><ent r="12" t="380" w="783" /></phr></stem><stem n="client"><phr n="Client"><ent r="4" t="0" w="94" /><ent r="4" t="0" w="116" /><ent r="4" t="0" w="138" /><ent r="3" t="1" w="128" /><ent r="4" t="3" w="26" /><ent r="5" t="5" w="209" /><ent r="4" t="6" w="23" /><ent r="1000" t="7" w="7" /><ent r="103" t="7" w="16" /><ent r="100" t="7" w="22" /><ent r="4" t="7" w="29" /><ent r="4" t="7" w="64" /><ent r="65" t="7" w="94" /><ent r="65" t="7" w="516" /><ent r="103" t="8" w="22" /><ent r="7" t="8" w="50" /><ent r="7" t="8" w="65" /><ent r="55" t="8" w="95" /><ent r="56" t="8" w="122" /><ent r="4" t="9" w="71" /><ent r="4" t="9" w="102" /><ent r="4" t="9" w="108" /><ent r="4" t="10" w="123" /><ent r="154" t="11" w="10" /><ent r="4" t="11" w="31" /><ent r="58" t="11" w="104" /><ent r="59" t="11" w="154" /><ent r="59" t="11" w="169" /><ent r="7" t="11" w="681" /><ent r="67" t="20" w="235" /><ent r="3" t="21" w="195" /><ent r="4" t="21" w="199" /><ent r="3" t="21" w="205" /><ent r="3" t="21" w="207" /><ent r="3" t="21" w="230" /><ent r="4" t="21" w="561" /><ent r="4" t="21" w="586" /><ent r="4" t="21" w="675" /><ent r="3" t="21" w="773" /><ent r="7" t="23" w="229" /><ent r="5" t="23" w="379" /><ent r="5" t="23" w="381" /><ent r="65" t="25" w="293" /><ent r="8" t="26" w="179" /><ent r="64" t="26" w="296" /><ent r="6" t="27" w="404" /><ent r="3" t="29" w="253" /><ent r="3" t="39" w="36" /><ent r="3" t="39" w="197" /><ent r="3" t="39" w="223" /><ent r="4" t="39" w="321" /><ent r="4" t="39" w="367" /><ent r="3" t="39" w="385" /><ent r="3" t="39" w="403" /><ent r="4" t="39" w="514" /><ent r="7" t="39" w="682" /><ent r="7" t="39" w="721" /><ent r="7" t="39" w="736" /><ent r="3" t="40" w="42" /><ent r="7" t="45" w="72" /><ent r="7" t="46" w="77" /><ent r="6" t="46" w="94" /><ent r="3" t="50" w="50" /><ent r="5" t="50" w="201" /><ent r="7" t="50" w="236" /><ent r="4" t="83" w="38" /><ent r="4" t="85" w="1089" /><ent r="5" t="85" w="1098" /><ent r="3" t="89" w="227" /><ent r="55" t="111" w="182" /><ent r="3" t="117" w="32" /><ent r="4" t="120" w="107" /><ent r="4" t="120" w="113" /><ent r="4" t="120" w="152" /><ent r="4" t="120" w="158" /><ent r="4" t="121" w="47" /><ent r="4" t="121" w="53" /><ent r="57" t="123" w="70" /><ent r="4" t="129" w="33" /><ent r="59" t="144" w="142" /><ent r="58" t="146" w="107" /><ent r="57" t="147" w="128" /><ent r="8" t="147" w="216" /><ent r="8" t="147" w="626" /><ent r="57" t="148" w="93" /><ent r="6" t="148" w="205" /><ent r="57" t="149" w="106" /><ent r="6" t="149" w="210" /><ent r="57" t="150" w="140" /><ent r="7" t="152" w="167" /><ent r="6" t="152" w="201" /><ent r="4" t="153" w="55" /><ent r="7" t="162" w="56" /><ent r="9" t="162" w="91" /><ent r="9" t="162" w="97" /><ent r="6" t="181" w="42" /><ent r="6" t="181" w="144" /><ent r="8" t="182" w="67" /><ent r="6" t="182" w="113" /><ent r="7" t="182" w="117" /><ent r="6" t="182" w="150" /><ent r="7" t="185" w="75" /><ent r="6" t="187" w="415" /><ent r="6" t="189" w="286" /><ent r="3" t="194" w="104" /><ent r="7" t="195" w="321" /><ent r="7" t="195" w="335" /><ent r="7" t="195" w="426" /><ent r="7" t="195" w="440" /><ent r="6" t="196" w="578" /><ent r="4" t="198" w="28" /><ent r="4" t="198" w="57" /><ent r="3" t="198" w="710" /><ent r="3" t="198" w="730" /><ent r="3" t="198" w="741" /><ent r="4" t="198" w="879" /><ent r="4" t="198" w="1007" /><ent r="100" t="198" w="1143" /><ent r="4" t="198" w="1148" /><ent r="4" t="198" w="1156" /><ent r="100" t="198" w="1165" /><ent r="4" t="198" w="1170" /><ent r="4" t="198" w="1180" /><ent r="3" t="198" w="1288" /><ent r="3" t="232" w="24" /><ent r="3" t="232" w="41" /><ent r="4" t="232" w="122" /><ent r="3" t="233" w="52" /><ent r="3" t="235" w="100" /><ent r="3" t="237" w="61" /><ent r="3" t="242" w="67" /><ent r="5" t="268" w="329" /><ent r="5" t="268" w="331" /><ent r="6" t="270" w="167" /><ent r="5" t="270" w="414" /><ent r="5" t="270" w="416" /><ent r="3" t="273" w="30" /><ent r="1000" t="274" w="3" /><ent r="102" t="274" w="23" /><ent r="3" t="274" w="29" /><ent r="5" t="274" w="84" /><ent r="6" t="282" w="419" /><ent r="4" t="307" w="32" /><ent r="64" t="307" w="105" /><ent r="4" t="308" w="23" /><ent r="3" t="335" w="25" /><ent r="4" t="342" w="147" /><ent r="9" t="380" w="215" /><ent r="6" t="380" w="334" /><ent r="9" t="380" w="722" /><ent r="6" t="380" w="883" /><ent r="57" t="382" w="67" /><ent r="65" t="392" w="229" /><ent r="65" t="394" w="431" /><ent r="55" t="399" w="91" /><ent r="4" t="399" w="155" /><ent r="4" t="399" w="211" /><ent r="5" t="399" w="724" /><ent r="4" t="400" w="21" /><ent r="4" t="400" w="56" /><ent r="6" t="400" w="341" /><ent r="55" t="408" w="52" /><ent r="55" t="429" w="75" /><ent r="5" t="430" w="36" /><ent r="100" t="432" w="9" /><ent r="7" t="432" w="123" /><ent r="6" t="432" w="153" /><ent r="6" t="432" w="223" /><ent r="10" t="433" w="94" /><ent r="9" t="433" w="404" /><ent r="5" t="445" w="98" /><ent r="4" t="445" w="448" /><ent r="4" t="445" w="723" /><ent r="5" t="445" w="752" /><ent r="4" t="480" w="69" /><ent r="59" t="488" w="462" /><ent r="59" t="498" w="102" /><ent r="8" t="502" w="470" /><ent r="6" t="525" w="352" /><ent r="4" t="554" w="37" /><ent r="55" t="554" w="56" /><ent r="4" t="563" w="49" /><ent r="4" t="588" w="43" /><ent r="6" t="588" w="116" /><ent r="5" t="610" w="59" /><ent r="100" t="619" w="20" /><ent r="100" t="619" w="26" /><ent r="3" t="619" w="49" /><ent r="1000" t="620" w="6" /><ent r="100" t="620" w="10" /><ent r="100" t="620" w="21" /><ent r="103" t="620" w="31" /><ent r="65" t="620" w="41" /><ent r="4" t="620" w="49" /><ent r="3" t="620" w="62" /><ent r="4" t="620" w="67" /><ent r="4" t="620" w="94" /><ent r="3" t="620" w="120" /><ent r="3" t="620" w="127" /><ent r="7" t="620" w="144" /><ent r="6" t="620" w="178" /><ent r="4" t="620" w="222" /><ent r="5" t="620" w="236" /><ent r="5" t="620" w="279" /><ent r="100" t="621" w="22" /><ent r="65" t="621" w="422" /><ent r="65" t="621" w="431" /><ent r="65" t="622" w="117" /><ent r="103" t="623" w="25" /><ent r="65" t="623" w="96" /><ent r="65" t="623" w="258" /><ent r="4" t="624" w="11" /><ent r="5" t="624" w="230" /><ent r="4" t="624" w="238" /><ent r="5" t="624" w="242" /><ent r="100" t="625" w="20" /><ent r="3" t="625" w="267" /><ent r="57" t="656" w="62" /><ent r="3" t="657" w="34" /><ent r="6" t="685" w="369" /><ent r="7" t="696" w="281" /><ent r="4" t="709" w="117" /></phr><phr n="Clients"><ent r="3" t="21" w="360" /><ent r="4" t="479" w="182" /></phr><phr n="client"><ent r="3" t="21" w="616" /><ent r="3" t="37" w="61" /><ent r="6" t="157" w="376" /><ent r="3" t="198" w="1196" /><ent r="100" t="274" w="8" /><ent r="6" t="412" w="424" /><ent r="6" t="435" w="86" /><ent r="6" t="436" w="85" /><ent r="6" t="588" w="126" /><ent r="4" t="624" w="250" /></phr><phr n="clients"><ent r="54" t="165" w="71" /><ent r="3" t="198" w="1384" /><ent r="3" t="625" w="89" /><ent r="54" t="625" w="212" /></phr></stem></index>